modules/__init__.py
modules/helper_func.py
modules/plot.py
modules/default/__init__.py
modules/default/helper_func_default.py
modules/default/libs_default.py
modules/default/plot_default.py
tests/__init__.py
tests/tests.py
jupyter_lib-0.1.2.dist-info/METADATA
jupyter_lib-0.1.2.dist-info/WHEEL
jupyter_lib-0.1.2.dist-info/top_level.txt
jupyter_lib-0.1.2.dist-info/RECORD
